{"cameraMode":{"drawMode":0,"name":"Shaded","section":"Shading Mode"},"sceneLighting":true,"audioPlay":false,"sceneViewState":{"m_AlwaysRefresh":false,"showFog":true,"showSkybox":true,"showFlares":true,"showImageEffects":true,"showParticleSystems":true,"showVisualEffectGraphs":true,"m_FxEnabled":true},"in2DMode":false,"pivot":{"x":-150.0,"y":-20.0,"z":0.0},"rotation":{"x":0.0009953679982572795,"y":0.09684831649065018,"z":-0.00009695962216937914,"w":0.9953014850616455},"size":141.42135620117188,"orthographic":false}